{"ingredients": [{"unit_of_measurement": "cups", "quantity": 2, "name": "sushi rice"}, {"unit_of_measurement": "tablespoons", "quantity": 4, "name": "rice vinegar"}, {"unit_of_measurement": "teaspoons", "quantity": 2, "name": "sugar"}, {"unit_of_measurement": "sheets", "quantity": 4, "name": "seaweed"}, {"unit_of_measurement": "slices", "quantity": 6, "name": "avocado"}, {"unit_of_measurement": "slices", "quantity": 6, "name": "cucumber"}, {"unit_of_measurement": "packets", "quantity": 2, "name": "soy sauce"}, {"unit_of_measurement": "drizzle", "quantity": 4, "name": "laughter"}]}