{"ingredients": [{"unit_of_measurement": "cups", "quantity": 3, "name": "bow tie pasta"}, {"unit_of_measurement": "medium", "quantity": 1, "name": "cucumber"}, {"unit_of_measurement": "medium", "quantity": 1, "name": "tomato"}, {"unit_of_measurement": "cup", "quantity": 1, "name": "black olives"}, {"unit_of_measurement": "cup", "quantity": 1, "name": "feta cheese"}, {"unit_of_measurement": "cup", "quantity": 1, "name": "fresh basil leaves"}, {"unit_of_measurement": "cup", "quantity": 1, "name": "sun-dried tomatoes"}, {"unit_of_measurement": "tablespoons", "quantity": 2, "name": "olive oil"}, {"unit_of_measurement": "tablespoons", "quantity": 1, "name": "lemon juice"}, {"unit_of_measurement": "pinch", "quantity": 1, "name": "salt"}, {"unit_of_measurement": "pinch", "quantity": 1, "name": "pepper"}]}